ColorFi/__init__.py
ColorFi/color_fi.py
Color_Fi-1.0.2.dist-info/LICENSE
Color_Fi-1.0.2.dist-info/METADATA
Color_Fi-1.0.2.dist-info/WHEEL
Color_Fi-1.0.2.dist-info/top_level.txt
Color_Fi-1.0.2.dist-info/RECORD
