Metadata-Version: 2.1
Name: Color-Fi
Version: 1.0.2
Summary: Color-Fi is a tool to color and format strings in python.
Home-page: https://github.com/johnjkenny/color-Fi
Author: John J Kenny
Author-email: johnjkenny88@gmail.com
License: UNKNOWN
Project-URL: Bug Tracker, https://github.com/johnjkenny/color-Fi/issues
Platform: UNKNOWN
Classifier: Programming Language :: Python :: 3
Classifier: License :: OSI Approved :: GNU Affero General Public License v3 or later (AGPLv3+)
Classifier: Operating System :: OS Independent
License-File: LICENSE
